{"P14": {"label": "\u6587\u6458", "labelColor": "#D0D91B", "postTitle": "\u4fe1\u3001\u671b\u3001\u7231", "postUrl": "post/xin-%E3%80%81-wang-%E3%80%81-ai.html", "commentNum": 0, "createdDate": "2024-02-04", "dateLabelColor": "#bc4c00"}, "P13": {"label": "\u4fe1\u4ef0", "labelColor": "#941128", "postTitle": "\u6b7b\u6d77\u53e4\u5377\u548c\u5723\u7ecf\u6284\u672c", "postUrl": "post/si-hai-gu-juan-he-sheng-jing-chao-ben.html", "commentNum": 0, "createdDate": "2024-01-30", "dateLabelColor": "#bc4c00"}, "P12": {"label": "\u6587\u6458", "labelColor": "#D0D91B", "postTitle": "\u6709\u7528\u7684\u793e\u4f1a\u89c4\u5219", "postUrl": "post/you-yong-de-she-hui-gui-ze.html", "commentNum": 0, "createdDate": "2024-01-30", "dateLabelColor": "#bc4c00"}, "P6": {"label": "\u6587\u6458", "labelColor": "#D0D91B", "postTitle": "\u7537\u4eba\u8fd9\u5473\u4e2d\u836f", "postUrl": "post/nan-ren-zhe-wei-zhong-yao.html", "commentNum": 0, "createdDate": "2024-01-30", "dateLabelColor": "#bc4c00"}, "P5": {"label": "\u6587\u6458", "labelColor": "#D0D91B", "postTitle": "\u7f8e\u56fd\u5988\u5988\u7ed9\u513f\u5b50\u7684\u624b\u673a\u4f7f\u7528\u6761\u6b3e", "postUrl": "post/mei-guo-ma-ma-gei-er-zi-de-shou-ji-shi-yong-tiao-kuan.html", "commentNum": 0, "createdDate": "2024-01-30", "dateLabelColor": "#bc4c00"}, "P4": {"label": "\u6587\u6458", "labelColor": "#D0D91B", "postTitle": "\u9893\u5e9f\u6587\u5b57", "postUrl": "post/tui-fei-wen-zi.html", "commentNum": 0, "createdDate": "2024-01-30", "dateLabelColor": "#bc4c00"}}